{
    "basic_info": {
      "description_header": "Hi",
      "description": "👋 I'm Erin Ranta. I am a software developer based out of New York City. I have always been in the field of helping people improve their lives, and now I strive to do that with technology. I also bring my creative eye with me and am excited to blend creativity with technology.",
      "section_name": {
        "about": "About me",
        "projects": "Projects",
        "skills": "Skills",
        "experience": "Experience"
      }
    },
    "projects": [
      {
        "title": "Odd-Duck",
        "startDate": "2022",
        "description": "This was a project from my 201 course where I implemented a random generator to gather and save data by saving clicks on a favorite image item from the user. Javascript, CSS, HTML, and Chart.js were used.",
        "images": [
          "images/portfolio/OddDuck.png"
        ],
        "url": "",
        "technologies": [
          {
            "class": "devicon-angularjs-plain",
            "name": "Angular"
          },
          {
            "class": "devicon-typescript-plain",
            "name": "TypeScript"
          },
          {
            "class": "devicon-csharp-plain",
            "name": "C#"
          }
        ]
      },
      {
        "title": "Cloud-Ten",
        "startDate": "2022",
        "description": "Cloud-Ten was our 201 group project. I worked on a lot of the front page styling, and a form that users enter data. It was my first time using animations via CSS. The project included Javascript, HTML, and CSS.",
        "images": [
          "images/portfolio/Cloudten.png",
          "images/portfolio/Cloudten.png"
        
        ],
        "url": "https://github.com",
        "technologies": [
          {
            "class": "devicon-react-original",
            "name": "React"
          },
          {
            "class": "devicon-javascript-plain",
            "name": "JavaScript"
          }
        ]
      },
      {
        "title": "3D Object Viewer",
        "startDate": "2015",
        "description": "One of the first apps I was working on my internship. I had to develop front-end implementation for app that shows 3D models of known buildings. This was also my first project in Angular framework. I've learned a lot!",
        "images": [
          "images/portfolio/adventure/p1.jpg",
          "images/portfolio/adventure/p2.jpg"
        ],
        "url": "https://github.com",
        "technologies": [
          {
            "class": "devicon-angularjs-plain",
            "name": "Angular"
          },
          {
            "class": "devicon-typescript-plain",
            "name": "TypeScript"
          },
          {
            "class": "devicon-csharp-plain",
            "name": "C#"
          }
        ]
      }
    ],
    "experience": [
      {
        "company": "DefOpenSource",
        "title": "Front-End Developer",
        "years": "10.2019 - present",
        "mainTech": [
          "Angular 8/9/10"
        ],
        "technologies": [
          "REST API",
          "RxJS",
          "JavaScript",
          "Bootstrap",
          "MDBootstrap",
          "EF Core",
          ".NET Core",
          "SignalR",
          "Angular Material"
        ]
      },
      {
        "company": "Serros Solutions",
        "title": "Intern",
        "years": "01.2018 - 09.2019",
        "mainTech": [
          "Angular 7/8"
        ],
        "technologies": [
          "RxJS",
          "Django",
          "PHP",
          "JavaScript",
          "DHTMLX Gantt"
        ]
      }
    ]
  }
